drsync/__init__.py
drsync/__main__.py
drsync/config.py
drsync/docker_interface.py
drsync/io_util.py
drsync/remote.py
drsync/subprocess_utils.py
drsync/sync.py
docker_remote_sync-0.7.0.dist-info/METADATA
docker_remote_sync-0.7.0.dist-info/WHEEL
docker_remote_sync-0.7.0.dist-info/entry_points.txt
docker_remote_sync-0.7.0.dist-info/licenses/LICENSE
docker_remote_sync-0.7.0.dist-info/RECORD
