Metadata-Version: 2.4
Name: docker-remote-sync
Version: 0.7.0
Summary: Utility to sync docker image between 2 docker host machines
Project-URL: Repository, https://github.com/tanavamsikrishna/docker-remote-sync
Author-email: Vamsi Talupula <tanavamsikrishna@outlook.com>
License-File: LICENSE
Requires-Python: ~=3.12
Requires-Dist: colorama
Requires-Dist: fabric
